chess_utils/__init__.py
chess_utils/__init__.pyi
chess_utils/boards.py
chess_utils/fens.py
chess_utils/misc.py
chess_utils/notations.py
chess_utils/test.py
chess_utils/pgns/__init__.py
chess_utils/pgns/__init__.pyi
chess_utils/pgns/export.py
chess_utils/pgns/read.py
chess_utils/pgns/types.py
chess_utils/random/__init__.py
chess_utils/random/random.py
chess_utils/test/test_parsing.py
chess_utils-0.1.19.dist-info/METADATA
chess_utils-0.1.19.dist-info/WHEEL
chess_utils-0.1.19.dist-info/top_level.txt
chess_utils-0.1.19.dist-info/RECORD
