Metadata-Version: 2.1
Name: chess-utils
Version: 0.1.19
Summary: Higher level utilities over the `chess` library
Author-email: Marcel Claramunt <marcel@moveread.com>
Requires-Python: >=3.10
Requires-Dist: chess
Requires-Dist: pydantic
Requires-Dist: lazy-loader
Requires-Dist: haskellian
Provides-Extra: test
Requires-Dist: pytest; extra == "test"
Requires-Dist: hypothesis; extra == "test"
